phishradar/__init__.py
phishradar/__main__.py
phishradar/constants.py
phishradar/processor.py
phishradar/output/__init__.py
phishradar/output/abstractoutputsink.py
phishradar/output/fileoutputsink.py
phishradar/output/logoutputsink.py
phishradar/output/weboutputsink.py
phishradar/tests/__init__.py
phishradar/tests/test_processor.py
phishradar-0.3.dist-info/LICENSE
phishradar-0.3.dist-info/METADATA
phishradar-0.3.dist-info/WHEEL
phishradar-0.3.dist-info/entry_points.txt
phishradar-0.3.dist-info/top_level.txt
phishradar-0.3.dist-info/RECORD
