Metadata-Version: 2.2
Name: phishradar
Version: 0.3
Summary: Phishing domain detection from Certificate Transparency logs.
Home-page: https://github.com/narekb/PhishRadar
Author: Narek Babajanyan
Author-email: narek_babajanyan@outlook.com
License: Apache Software License (Apache 2.0)
Project-URL: Source, https://github.com/narekb/PhishRadar
Classifier: Environment :: Console
Classifier: Intended Audience :: Information Technology
Classifier: Topic :: Security
Requires-Python: >=3.13
License-File: LICENSE
Requires-Dist: certstream
Requires-Dist: PyYAML
Requires-Dist: wordsegment
Requires-Dist: aiohttp
Dynamic: author
Dynamic: author-email
Dynamic: classifier
Dynamic: description
Dynamic: description-content-type
Dynamic: home-page
Dynamic: license
Dynamic: project-url
Dynamic: requires-dist
Dynamic: requires-python
Dynamic: summary
